LICENSE
MANIFEST.in
README.md
setup.cfg
setup.py
csengine/__init__.py
csengine/app.py
csengine/command.py
csengine/component.py
csengine/observer.py
csengine/service.py
csengine/view.py
csengine.egg-info/PKG-INFO
csengine.egg-info/SOURCES.txt
csengine.egg-info/dependency_links.txt
csengine.egg-info/requires.txt
csengine.egg-info/top_level.txt
csengine/blobstorage/__init__.py
csengine/blobstorage/config.py
csengine/blobstorage/provider.py
csengine/blobstorage/service.py
csengine/blobstorage/providers/__init__.py
csengine/blobstorage/providers/aioredis.py
csengine/blobstorage/providers/gcloud.py
csengine/blobstorage/providers/gcloud_aio.py
csengine/blobstorage/providers/local.py
csengine/blobstorage/providers/redis.py
csengine/db/__init__.py
csengine/db/config.py
csengine/db/manager.py
csengine/db/provider.py
csengine/db/service.py
csengine/db/providers/__init__.py
csengine/db/providers/aioredis.py
csengine/db/providers/asynces.py
csengine/db/providers/es.py
csengine/db/providers/redis.py
csengine/db/services/__init__.py
csengine/db/services/aioredis.py
csengine/db/services/es.py
csengine/db/services/redis.py
csengine/extentions/__init__.py
csengine/extentions/aiohttp/__init__.py
csengine/extentions/fastapi/__init__.py
csengine/extentions/fastapi/app.py
csengine/extentions/fastapi/view/__init__.py
csengine/extentions/fastapi/view/events.py
csengine/extentions/fastapi/view/exceptions.py
csengine/extentions/fastapi/view/health.py
csengine/extentions/fastapi/view/metrics.py
csengine/extentions/fastapi/view/models.py
csengine/extentions/fastapi/view/serializers.py
csengine/extentions/fastapi/view/system.py
csengine/extentions/fastapi/view/tracing.py
csengine/extentions/fastapi/view/view.py
csengine/extentions/gcloud/__init__.py
csengine/extentions/gcloud/client.py
csengine/extentions/gcloud/clients/__init__.py
csengine/extentions/gcloud/clients/aio_storage.py
csengine/extentions/gcloud/clients/storage.py
csengine/extentions/redis/__init__.py
csengine/extentions/redis/client.py
csengine/extentions/redis/clients/__init__.py
csengine/extentions/redis/clients/aioredis.py
csengine/extentions/redis/clients/redis.py
